agentloop/__init__.py
agentloop/main.py
agentloop/actions/__init__.py
agentloop/actions/executor.py
agentloop/core/__init__.py
agentloop/core/agent.py
agentloop/core/schemas.py
agentloop/llm/__init__.py
agentloop/llm/decision_engine.py
autonomous_agentloop-0.1.1.dist-info/METADATA
autonomous_agentloop-0.1.1.dist-info/WHEEL
autonomous_agentloop-0.1.1.dist-info/entry_points.txt
autonomous_agentloop-0.1.1.dist-info/licenses/LICENSE
autonomous_agentloop-0.1.1.dist-info/RECORD
