Metadata-Version: 2.4
Name: autonomous-agentloop
Version: 0.1.1
Summary: An autonomous agent system demonstrating LLM-based decision-making in a closed-loop control architecture
Project-URL: Homepage, https://github.com/Guri10/AgentLoop
Project-URL: Repository, https://github.com/Guri10/AgentLoop
Project-URL: Documentation, https://github.com/Guri10/AgentLoop#readme
Project-URL: Issues, https://github.com/Guri10/AgentLoop/issues
Author: AgentLoop Contributors
License: MIT
License-File: LICENSE
Keywords: agents,ai,autonomous,decision-making,llm,openai
Classifier: Development Status :: 4 - Beta
Classifier: Intended Audience :: Developers
Classifier: License :: OSI Approved :: MIT License
Classifier: Programming Language :: Python :: 3
Classifier: Programming Language :: Python :: 3.11
Classifier: Programming Language :: Python :: 3.12
Classifier: Topic :: Scientific/Engineering :: Artificial Intelligence
Requires-Python: >=3.11
Requires-Dist: beautifulsoup4>=4.12.0
Requires-Dist: openai>=1.12.0
Requires-Dist: pydantic>=2.6.0
Requires-Dist: python-dotenv>=1.0.0
Requires-Dist: requests>=2.31.0
Provides-Extra: dev
Requires-Dist: black>=24.0.0; extra == 'dev'
Requires-Dist: pytest-asyncio>=0.23.0; extra == 'dev'
Requires-Dist: pytest>=8.0.0; extra == 'dev'
Requires-Dist: ruff>=0.2.0; extra == 'dev'
Provides-Extra: web
Requires-Dist: plotly>=5.18.0; extra == 'web'
Requires-Dist: streamlit>=1.31.0; extra == 'web'
